{"textures":{"0":"modelengine:entity/texture"},"elements":[{"from":[5.8500004,6.0,5.25],"to":[9.0,10.0,8.75],"faces":{"east":{"uv":[9.625,4.75,10.125,5.25],"tintindex":0,"rotation":0,"texture":"#0"},"south":{"uv":[9.875,10.0,10.25,10.5],"tintindex":0,"rotation":0,"texture":"#0"},"north":{"uv":[6.5,5.375,6.875,5.875],"tintindex":0,"rotation":0,"texture":"#0"},"west":{"uv":[9.625,5.25,10.125,5.75],"tintindex":0,"rotation":0,"texture":"#0"},"up":{"uv":[10.5,0.5,10.125,0.0],"tintindex":0,"rotation":0,"texture":"#0"},"down":{"uv":[10.5,4.75,10.125,5.25],"tintindex":0,"rotation":0,"texture":"#0"}}},{"from":[6.1000004,2.0,5.6],"to":[8.75,9.0,8.6],"faces":{"east":{"uv":[8.5,7.875,8.875,8.75],"tintindex":0,"rotation":0,"texture":"#0"},"south":{"uv":[4.375,8.625,4.75,9.5],"tintindex":0,"rotation":0,"texture":"#0"},"north":{"uv":[2.0,6.25,2.375,7.125],"tintindex":0,"rotation":0,"texture":"#0"},"west":{"uv":[4.75,8.625,5.125,9.5],"tintindex":0,"rotation":0,"texture":"#0"},"up":{"uv":[3.125,11.0,2.75,10.625],"tintindex":0,"rotation":0,"texture":"#0"},"down":{"uv":[11.0,2.75,10.625,3.125],"tintindex":0,"rotation":0,"texture":"#0"}}}],"display":{"gui":{"rotation":[30,225,0]}}}